setup.py
hamlpy/__init__.py
hamlpy/elements.py
hamlpy/hamlpy.py
hamlpy/hamlpy_watcher.py
hamlpy/nodes.py
hamlpy/templatize.py
hamlpy.egg-info/PKG-INFO
hamlpy.egg-info/SOURCES.txt
hamlpy.egg-info/dependency_links.txt
hamlpy.egg-info/entry_points.txt
hamlpy.egg-info/requires.txt
hamlpy.egg-info/top_level.txt
hamlpy/template/__init__.py
hamlpy/template/loaders.py
hamlpy/template/utils.py