Metadata-Version: 1.0
Name: hamlpy
Version: 0.82.2
Summary: HAML like syntax for Django templates
Home-page: http://github.com/jessemiller/HamlPy
Author: Jesse Miller
Author-email: millerjesse@gmail.com
License: MIT
Download-URL: git@github.com:jessemiller/HamlPy.git
Keywords: haml django converter
Platform: UNKNOWN
